__init__.py
src/paiclient/__init__.py
src/paiclient/objects.py
src/paiclient/pai_client.py
src/paiclient/components/__init__.py
src/paiclient/components/pai_requests.py
src/paiclient/components/pai_responses.py
src/paiclient/components/pai_uris.py
src/paiclient/components/request_objects.py
pai_thin_client-1.0.2.dist-info/METADATA
pai_thin_client-1.0.2.dist-info/WHEEL
pai_thin_client-1.0.2.dist-info/licenses/LICENSE
pai_thin_client-1.0.2.dist-info/RECORD
