Metadata-Version: 2.1
Name: pai_thin_client
Version: 1.0.2
Summary: A thin client for communicating with the Private Ai de-identication api.
Project-URL: Homepage, https://github.com/privateai/pai_thin_client/
Project-URL: Bug Tracker, https://github.com/privateai/pai_thin_client/issues
Author-email: Adam Guiducci <adam.guiducci@private-ai.com>
License-File: LICENSE
Classifier: License :: OSI Approved :: MIT License
Classifier: Operating System :: OS Independent
Classifier: Programming Language :: Python :: 3
Requires-Python: >=3.8
